MANIFEST.in
README.md
setup.py
SizeFS.egg-info/PKG-INFO
SizeFS.egg-info/SOURCES.txt
SizeFS.egg-info/dependency_links.txt
SizeFS.egg-info/requires.txt
SizeFS.egg-info/top_level.txt
sizefs/__init__.py
sizefs/contents.py
sizefs/sizefs.py
sizefs/sizefsFuse.py
tests/__init__.py
tests/conftest.py
tests/test_contents.py
tests/test_sfs.py
tests/test_sizefsFuse.py