Metadata-Version: 1.1
Name: SizeFS
Version: 0.4.0
Summary: SizeFS is a mock filesystem for creating files of particular sizes with specified contents.
Home-page: http://pypi.python.org/pypi/SizeFS/
Author: Sohonet
Author-email: dev@sohonet.com
License: LICENSE.txt
Download-URL: https://github.com/sohonetlabs/sizefs
Keywords: testing,files,size
Platform: UNKNOWN
